gmo_fx/__init__.py
gmo_fx/common.py
gmo_fx/errors.py
gmo_fx/urls.py
gmo_fx/api/__init__.py
gmo_fx/api/api_base.py
gmo_fx/api/assets.py
gmo_fx/api/change_oco_order.py
gmo_fx/api/close_order.py
gmo_fx/api/executions.py
gmo_fx/api/klines.py
gmo_fx/api/latest_executions.py
gmo_fx/api/open_positions.py
gmo_fx/api/order.py
gmo_fx/api/orders.py
gmo_fx/api/position_summary.py
gmo_fx/api/response.py
gmo_fx/api/status.py
gmo_fx/api/symbols.py
gmo_fx/api/ticker.py
gmo_fx-0.9.1.dist-info/licenses/LICENSE
tests/__init__.py
tests/api_test_base.py
tests/test_api_base.py
tests/test_assets.py
tests/test_base_response.py
tests/test_change_oco_order.py
tests/test_close_order.py
tests/test_executions.py
tests/test_klines.py
tests/test_latest_executions.py
tests/test_open_positions.py
tests/test_order.py
tests/test_orders.py
tests/test_position_summary.py
tests/test_status.py
tests/test_symbols.py
tests/test_ticker.py
gmo_fx-0.9.1.dist-info/METADATA
gmo_fx-0.9.1.dist-info/WHEEL
gmo_fx-0.9.1.dist-info/top_level.txt
gmo_fx-0.9.1.dist-info/RECORD
