Metadata-Version: 2.4
Name: gmo_fx
Version: 0.9.1
Summary: GMO社のFX API用Pythonライブラリ
Home-page: https://github.com/RikitoNoto/gmo-fx-py
Download-URL: https://github.com/RikitoNoto/gmo-fx-py
Author: Rikito Noto
Author-email: rikitonoto@gmail.com
License: MIT
License-File: LICENSE
Requires-Dist: requests>=2.31.0
Dynamic: author
Dynamic: author-email
Dynamic: description
Dynamic: description-content-type
Dynamic: download-url
Dynamic: home-page
Dynamic: license
Dynamic: license-file
Dynamic: requires-dist
Dynamic: summary
